{
   "data": [
      {
         "movie": "机械师2:复活",
         "movieStyle": "原版2D",
         "oldPrice": "80",
         "newPrice": "68",
         "imgUrl": "https://img.alicdn.com/bao/uploaded/i3/TB1LgCUNpXXXXbZXXXXXXXXXXXX_.jpg_160x240.jpg",
         "star": "8.7",
         "daoyan": "丹尼斯·甘赛尔",
         "mainStar": "杰森·斯坦森,杰西卡·阿尔芭,汤米·李·琼斯,杨紫琼,山姆·哈兹尔丁",
         "style": "动作 犯罪",
         "address": "美国 泰国 法国",
         "people": "27872",
         "language": "英语",
         "time": "97分钟",
         "date": "10-28",
         "method": "选座购票",
         "content": "故事时间则设定为前作的五年之后，亚瑟已然选择金盆洗手，与挚爱吉娜（杰西卡·阿尔芭 饰）隐姓埋名地共度美好人生。然而像亚瑟这种高手想要全身而退谈何容易，反派最终绑架了吉娜来要挟亚瑟，让他去杀三个人。所谓敌人的敌人就是朋友，亚瑟随后便与刺杀名单上的麦克斯（汤姆·李·琼斯 饰）结成同盟，一同对付他们共同的对手。"
      },
      {
         "movie": "惊天破",
         "movieStyle": "原版3D",
         "oldPrice": "80",
         "newPrice": "68",
         "imgUrl": "https://img.alicdn.com/bao/uploaded/i3/TB1EsW8NFXXXXXUapXXXXXXXXXX_.jpg_160x240.jpg",
         "star": "7.1",
         "daoyan": "吴品儒",
         "mainStar": "谢霆锋,刘青云,佟丽娅,范晓萱",
         "style": "警匪 动作 剧情 犯罪",
         "address": "中国 中国香港",
         "people": "27341",
         "language": "汉语普通话 粤语",
         "time": "103分钟",
         "date": "10-28",
         "method": "选座购票",
         "content": "在一次追捕行动中,警察马进(谢霆锋饰)击毙连环杀手,却被对方射穿心脏,命悬一线，意外之下接受了心脏移植手术，时隔2年，国际惊现数宗手法完全一致的惊天大案，康复后的马金主动请缨，与犯罪心理学教授车家伟(刘青云饰)联手展开调查。"
      },
      {
         "movie": "侠探杰克：永不回头",
         "movieStyle": "原版3D",
         "oldPrice": "80",
         "newPrice": "68",
         "imgUrl": "https://img.alicdn.com/bao/uploaded/i4/TB1X31pNpXXXXX9aXXXXXXXXXXX_.jpg_160x240.jpg",
         "star": "8.2",
         "daoyan": "爱德华·兹威克",
         "mainStar": "汤姆·克鲁斯,寇碧·史莫德斯,阿尔迪斯·霍奇,达妮卡·亚罗什,罗伯特·克耐普",
         "style": "动作 冒险 犯罪",
         "address": "美国",
         "people": "32141",
         "language": "英语",
         "time": "118分钟",
         "date": "10-28",
         "method": "选座购票",
         "content": "在一次追捕行动中,警察马进(谢霆锋饰)击毙连环杀手,却被对方射穿心脏,命悬一线，意外之下接受了心脏移植手术，时隔2年，国际惊现数宗手法完全一致的惊天大案，康复后的马金主动请缨，与犯罪心理学教授车家伟(刘青云饰)联手展开调查。"
      },
      {
         "movie": "机械师2:复活",
         "movieStyle": "原版2D",
         "oldPrice": "80",
         "newPrice": "68",
         "imgUrl": "https://img.alicdn.com/bao/uploaded/i3/TB1LgCUNpXXXXbZXXXXXXXXXXXX_.jpg_160x240.jpg",
         "star": "8.7",
         "daoyan": "丹尼斯·甘赛尔",
         "mainStar": "杰森·斯坦森,杰西卡·阿尔芭,汤米·李·琼斯,杨紫琼,山姆·哈兹尔丁",
         "style": "动作 犯罪",
         "address": "美国 泰国 法国",
         "people": "27872",
         "language": "英语",
         "time": "97分钟",
         "date": "10-28",
         "method": "选座购票",
         "content": "故事时间则设定为前作的五年之后，亚瑟已然选择金盆洗手，与挚爱吉娜（杰西卡·阿尔芭 饰）隐姓埋名地共度美好人生。然而像亚瑟这种高手想要全身而退谈何容易，反派最终绑架了吉娜来要挟亚瑟，让他去杀三个人。所谓敌人的敌人就是朋友，亚瑟随后便与刺杀名单上的麦克斯（汤姆·李·琼斯 饰）结成同盟，一同对付他们共同的对手。"
      },
      {
         "movie": "惊天破",
         "movieStyle": "原版3D",
         "oldPrice": "80",
         "newPrice": "68",
         "imgUrl": "https://img.alicdn.com/bao/uploaded/i3/TB1EsW8NFXXXXXUapXXXXXXXXXX_.jpg_160x240.jpg",
         "star": "7.1",
         "daoyan": "吴品儒",
         "mainStar": "谢霆锋,刘青云,佟丽娅,范晓萱",
         "style": "警匪 动作 剧情 犯罪",
         "address": "中国 中国香港",
         "people": "27341",
         "language": "汉语普通话 粤语",
         "time": "103分钟",
         "date": "10-28",
         "method": "选座购票",
         "content": "在一次追捕行动中,警察马进(谢霆锋饰)击毙连环杀手,却被对方射穿心脏,命悬一线，意外之下接受了心脏移植手术，时隔2年，国际惊现数宗手法完全一致的惊天大案，康复后的马金主动请缨，与犯罪心理学教授车家伟(刘青云饰)联手展开调查。"
      },
      {
         "movie": "侠探杰克：永不回头",
         "movieStyle": "原版3D",
         "oldPrice": "80",
         "newPrice": "68",
         "imgUrl": "https://img.alicdn.com/bao/uploaded/i4/TB1X31pNpXXXXX9aXXXXXXXXXXX_.jpg_160x240.jpg",
         "star": "8.2",
         "daoyan": "爱德华·兹威克",
         "mainStar": "汤姆·克鲁斯,寇碧·史莫德斯,阿尔迪斯·霍奇,达妮卡·亚罗什,罗伯特·克耐普",
         "style": "动作 冒险 犯罪",
         "address": "美国",
         "people": "32141",
         "language": "英语",
         "time": "118分钟",
         "date": "10-28",
         "method": "选座购票",
         "content": "在一次追捕行动中,警察马进(谢霆锋饰)击毙连环杀手,却被对方射穿心脏,命悬一线，意外之下接受了心脏移植手术，时隔2年，国际惊现数宗手法完全一致的惊天大案，康复后的马金主动请缨，与犯罪心理学教授车家伟(刘青云饰)联手展开调查。"
      },
      {
         "movie": "机械师2:复活",
         "movieStyle": "原版2D",
         "oldPrice": "80",
         "newPrice": "68",
         "imgUrl": "https://img.alicdn.com/bao/uploaded/i3/TB1LgCUNpXXXXbZXXXXXXXXXXXX_.jpg_160x240.jpg",
         "star": "8.7",
         "daoyan": "丹尼斯·甘赛尔",
         "mainStar": "杰森·斯坦森,杰西卡·阿尔芭,汤米·李·琼斯,杨紫琼,山姆·哈兹尔丁",
         "style": "动作 犯罪",
         "address": "美国 泰国 法国",
         "people": "27872",
         "language": "英语",
         "time": "97分钟",
         "date": "10-28",
         "method": "选座购票",
         "content": "故事时间则设定为前作的五年之后，亚瑟已然选择金盆洗手，与挚爱吉娜（杰西卡·阿尔芭 饰）隐姓埋名地共度美好人生。然而像亚瑟这种高手想要全身而退谈何容易，反派最终绑架了吉娜来要挟亚瑟，让他去杀三个人。所谓敌人的敌人就是朋友，亚瑟随后便与刺杀名单上的麦克斯（汤姆·李·琼斯 饰）结成同盟，一同对付他们共同的对手。"
      },
      {
         "movie": "惊天破",
         "movieStyle": "原版3D",
         "oldPrice": "80",
         "newPrice": "68",
         "imgUrl": "https://img.alicdn.com/bao/uploaded/i3/TB1EsW8NFXXXXXUapXXXXXXXXXX_.jpg_160x240.jpg",
         "star": "7.1",
         "daoyan": "吴品儒",
         "mainStar": "谢霆锋,刘青云,佟丽娅,范晓萱",
         "style": "警匪 动作 剧情 犯罪",
         "address": "中国 中国香港",
         "people": "27341",
         "language": "汉语普通话 粤语",
         "time": "103分钟",
         "date": "10-28",
         "method": "选座购票",
         "content": "在一次追捕行动中,警察马进(谢霆锋饰)击毙连环杀手,却被对方射穿心脏,命悬一线，意外之下接受了心脏移植手术，时隔2年，国际惊现数宗手法完全一致的惊天大案，康复后的马金主动请缨，与犯罪心理学教授车家伟(刘青云饰)联手展开调查。"
      },
      {
         "movie": "侠探杰克：永不回头",
         "movieStyle": "原版3D",
         "oldPrice": "80",
         "newPrice": "68",
         "imgUrl": "https://img.alicdn.com/bao/uploaded/i4/TB1X31pNpXXXXX9aXXXXXXXXXXX_.jpg_160x240.jpg",
         "star": "8.2",
         "daoyan": "爱德华·兹威克",
         "mainStar": "汤姆·克鲁斯,寇碧·史莫德斯,阿尔迪斯·霍奇,达妮卡·亚罗什,罗伯特·克耐普",
         "style": "动作 冒险 犯罪",
         "address": "美国",
         "people": "32141",
         "language": "英语",
         "time": "118分钟",
         "date": "10-28",
         "method": "选座购票",
         "content": "在一次追捕行动中,警察马进(谢霆锋饰)击毙连环杀手,却被对方射穿心脏,命悬一线，意外之下接受了心脏移植手术，时隔2年，国际惊现数宗手法完全一致的惊天大案，康复后的马金主动请缨，与犯罪心理学教授车家伟(刘青云饰)联手展开调查。"
     }
   ]
}
